{
  "project_info": {
    "project_number": "1083702732005",
    "project_id": "relaxtime-53d6b",
    "storage_bucket": "relaxtime-53d6b.appspot.com"
  },
  "client": [
    {
      "client_info": {
        "mobilesdk_app_id": "1:1083702732005:android:7d95a7c67d6b573a98600c",
        "android_client_info": {
          "package_name": "com.example.relaxtime"
        }
      },
      "oauth_client": [
        {
          "client_id": "1083702732005-r9oecj1njgpomcotf8ao946ubl8iv2og.apps.googleusercontent.com",
          "client_type": 3
        }
      ],
      "api_key": [
        {
          "current_key": "AIzaSyD66irN0QTtAXWzUXQKd-RNN1zo_FkSkNw"
        }
      ],
      "services": {
        "appinvite_service": {
          "other_platform_oauth_client": [
            {
              "client_id": "1083702732005-r9oecj1njgpomcotf8ao946ubl8iv2og.apps.googleusercontent.com",
              "client_type": 3
            }
          ]
        }
      }
    }
  ],
  "configuration_version": "1"
}